type_hint_checker/__init__.py
type_hint_checker/_lib.py
rj_type_hint_checker-0.0.0.dist-info/LICENSE
rj_type_hint_checker-0.0.0.dist-info/METADATA
rj_type_hint_checker-0.0.0.dist-info/WHEEL
rj_type_hint_checker-0.0.0.dist-info/top_level.txt
rj_type_hint_checker-0.0.0.dist-info/RECORD
