Metadata-Version: 2.1
Name: rj-type-hint-checker
Version: 0.0.0
Summary: a rough equivilent of isinstance that works with type hints
Author: RJ_Infinity
License: MIT License
Project-URL: Homepage, https://github.com/RJ-Infinity/type_hint_checker
Project-URL: Documentation, https://github.com/RJ-Infinity/type_hint_checker
Project-URL: Repository, https://github.com/RJ-Infinity/type_hint_checker
Project-URL: Issues, https://github.com/RJ-Infinity/type_hint_checker/issues
Keywords: isinstance,type hints,types
Classifier: Programming Language :: Python :: 3
Classifier: License :: OSI Approved :: MIT License
Classifier: Operating System :: OS Independent
Requires-Python: >=3.12
License-File: LICENSE
